Compiled from "GaussSumBitshift.java"
public class GaussSumBitshift {
  public GaussSumBitshift();
    Code:
       0: aload_0
       1: invokespecial #1                  // Method java/lang/Object."<init>":()V
       4: return

  public static void main(java.lang.String[]);
    Code:
       0: getstatic     #2                  // Field java/lang/System.out:Ljava/io/PrintStream;
       3: ldc           #3                  // String Gauss Summation for n = 10 by bitshift:
       5: invokevirtual #4                  // Method java/io/PrintStream.print:(Ljava/lang/String;)V
       8: getstatic     #2                  // Field java/lang/System.out:Ljava/io/PrintStream;
      11: ldc2_w        #5                  // long 10l
      14: invokestatic  #7                  // Method gaussSumByBitshift:(J)J
      17: invokevirtual #8                  // Method java/io/PrintStream.println:(J)V
      20: return

  public static long gaussSumByBitshift(long);
    Code:
       0: lload_0
       1: lload_0
       2: lconst_1
       3: ladd
       4: lmul
       5: iconst_1
       6: lshr
       7: lreturn
}